autorank/__init__.py
autorank/_util.py
autorank/autorank.py
tests/__init__.py
tests/test_autorank.py
autorank-1.3.0.dist-info/LICENSE
autorank-1.3.0.dist-info/METADATA
autorank-1.3.0.dist-info/WHEEL
autorank-1.3.0.dist-info/top_level.txt
autorank-1.3.0.dist-info/RECORD
