Metadata-Version: 2.1
Name: autorank
Version: 1.3.0
Summary: Automated ranking of populations in a repeated measures experiment, e.g., to rank different machine learning approaches tested on the same data.
Home-page: https://github.com/sherbold/autorank
Download-URL: https://github.com/sherbold/autorank/zipball/master
Author: sherbold
Author-email: steffen.herbold@uni-passau.de
Classifier: Programming Language :: Python :: 3
Classifier: Development Status :: 4 - Beta
Classifier: Environment :: Console
Classifier: Intended Audience :: Developers
Classifier: License :: OSI Approved :: Apache Software License
Classifier: Operating System :: POSIX :: Linux
Classifier: Topic :: Scientific/Engineering
License-File: LICENSE
Requires-Dist: numpy
Requires-Dist: pandas>=2.0.3
Requires-Dist: statsmodels>=0.14.0
Requires-Dist: scipy>=1.10.1
Requires-Dist: matplotlib>=3.7.2
Requires-Dist: baycomp>=1.0.3
Requires-Dist: jinja2>=3.1.2
